{"zoom": 0.9853854105679156, "node_charge": -100, "node_gravity": 0, "link_distance": 50, "link_distance_variation": 1, "node_collision": true, "wiggle_nodes": false, "freeze_nodes": false, "node_fill_color": "#79aaa0", "node_stroke_color": "#555555", "node_label_color": "#000000", "display_node_labels": false, "scale_node_size_by_strength": true, "node_size": 19.836054138612415, "node_stroke_width": 0.9695527480971897, "node_size_variation": 0.5, "link_color": "#000000", "link_width": 7.131740213791715, "link_alpha": 0.7433252982289227, "link_width_variation": 1.1620602038202577, "display_singleton_nodes": true, "min_link_weight_percentile": 0, "max_link_weight_percentile": 1}